xgboost_model/.DS_Store
xgboost_model/VERSION
xgboost_model/__init__.py
xgboost_model/pipeline.py
xgboost_model/predict.py
xgboost_model/train_model.py
xgboost_model/config/__init__.py
xgboost_model/config/config.py
xgboost_model/datasets/properties-80210.csv
xgboost_model/processing/data_management.py
xgboost_model/processing/features.py
xgboost_model/processing/preprocessing.py
xgboost_model/trained_models/xgboost_v0.1.0.pkl
xgboost_model/trained_models/xgboost_v0.1.2.pkl
xgboost_model-0.1.2.dist-info/LICENSE
xgboost_model-0.1.2.dist-info/METADATA
xgboost_model-0.1.2.dist-info/WHEEL
xgboost_model-0.1.2.dist-info/top_level.txt
xgboost_model-0.1.2.dist-info/RECORD
